elastic_warping_vis/__init__.py
elastic_warping_vis/draw_functions.py
elastic_warping_vis/utils.py
elastic_warping_vis-0.2.1.dist-info/LICENSE
elastic_warping_vis-0.2.1.dist-info/METADATA
elastic_warping_vis-0.2.1.dist-info/WHEEL
elastic_warping_vis-0.2.1.dist-info/top_level.txt
elastic_warping_vis-0.2.1.dist-info/RECORD
