Metadata-Version: 2.1
Name: elastic_warping_vis
Version: 0.2.1
Summary: Visualization of Elastic Warping of Time Series Data 
Author-email: Ali Ismail-Fawaz <ali-el-hadi.ismail-fawaz@uha.fr>, Maxime Devanne <maxime.devanne@uha.fr>, Stefano Berretti <stefano.berretti@unifi.it>, Jonathan Weber <jonathan.weber@uha.fr>, Germain Forestier <germain.forestier@uha.fr>
Maintainer-email: Ali Ismail-Fawaz <ali-el-hadi.ismail-fawaz@uha.fr>
License: GPL-3.0-only
Keywords: data-science,machine-learning,data-mining,time-series,dynamic-time-warping,elastic-similarity-measures,elastic-distances,time-series-analysis,time-series-classification,time-series-regression,time-series-machine-learning,data-visualization
Classifier: Development Status :: 4 - Beta
Classifier: Intended Audience :: Developers
Classifier: License :: OSI Approved :: GNU General Public License v3 (GPLv3)
Classifier: Programming Language :: Python :: 3
Classifier: Programming Language :: Python :: 3.10
Classifier: Programming Language :: Python :: 3.11
Classifier: Programming Language :: Python :: 3.12
Requires-Python: >=3.10
License-File: LICENSE
Requires-Dist: numpy ==1.26.4
Requires-Dist: aeon ==0.10.0
Requires-Dist: hydra-core ==1.3.2
Requires-Dist: omegaconf ==2.3.0
Requires-Dist: matplotlib ==3.9.0
Provides-Extra: dev
Requires-Dist: black ; extra == 'dev'
Requires-Dist: flake8 ; extra == 'dev'
Requires-Dist: mypy ; extra == 'dev'
Requires-Dist: pytest ; extra == 'dev'
Requires-Dist: pytest-cov ; extra == 'dev'
Requires-Dist: pytest-xdist ; extra == 'dev'
Requires-Dist: pytest-timeout ; extra == 'dev'
Requires-Dist: pytest-rerunfailures ; extra == 'dev'
Requires-Dist: pre-commit ; extra == 'dev'
